pp_iopm/Connector.py
pp_iopm/Handover.py
pp_iopm/IOPM.py
pp_iopm/Organization.py
pp_iopm/__init__.py
pp_iopm-0.0.1.dist-info/LICENSE
pp_iopm-0.0.1.dist-info/METADATA
pp_iopm-0.0.1.dist-info/WHEEL
pp_iopm-0.0.1.dist-info/top_level.txt
pp_iopm-0.0.1.dist-info/RECORD
