Metadata-Version: 2.1
Name: pp-iopm
Version: 0.0.1
Summary: An Abstraction-Based Approach for Privacy-Aware Inter-Organizational Process Mining
Home-page: https://github.com/m4jidRafiei/pp-iopm
Author: Majid Rafiei
Author-email: majid.rafiei@pads.rwth-aachen.de
License: UNKNOWN
Project-URL: Source, https://github.com/m4jidRafiei/pp-iopm
Platform: UNKNOWN
Classifier: Programming Language :: Python :: 3
Classifier: License :: OSI Approved :: GNU General Public License v3 (GPLv3)
Classifier: Operating System :: OS Independent
License-File: LICENSE
Requires-Dist: pm4py (>=2.2.18)
